easy_kindle.py
easy_kindle-0.0.1.dist-info/METADATA
easy_kindle-0.0.1.dist-info/WHEEL
easy_kindle-0.0.1.dist-info/entry_points.txt
easy_kindle-0.0.1.dist-info/top_level.txt
easy_kindle-0.0.1.dist-info/RECORD
