Metadata-Version: 2.1
Name: easy-kindle
Version: 0.0.1
Summary: Send documents to kindle from the command line.
Home-page: https://github.com/itsron717/easy-kindle
Author: Rounak Vyas
Author-email: itsron143@gmail.com
License: MIT
Platform: UNKNOWN
Requires-Dist: click
Requires-Dist: stdiomask
Requires-Dist: appdirs
